{"commitInfo":{"timestamp":1772797018645,"operation":"STREAMING UPDATE","operationParameters":{"outputMode":"Append","queryId":"f1911315-df3a-4229-8af9-26d94ce6b160","epochId":"1"},"readVersion":0,"isolationLevel":"Serializable","isBlindAppend":true,"operationMetrics":{"numRemovedFiles":"0","numOutputRows":"2","numOutputBytes":"3810","numAddedFiles":"1"},"engineInfo":"Apache-Spark/3.4.1 Delta-Lake/2.4.0","txnId":"9ec1ed0c-0ee0-4af3-9d77-5c1c4171c473"}}
{"txn":{"appId":"f1911315-df3a-4229-8af9-26d94ce6b160","version":1,"lastUpdated":1772797018645}}
{"add":{"path":"part-00000-7d6f03a9-4dfc-4eae-9397-b531e8abb79b-c000.snappy.parquet","partitionValues":{},"size":3810,"modificationTime":1772797018609,"dataChange":true,"stats":"{\"numRecords\":2,\"minValues\":{\"transaction_id\":\"77eb431e-09e6-4406-8607-73d3190c\",\"user_id\":\"USR_0001\",\"amount\":420.91,\"currency\":\"USD\",\"merchant_id\":\"MER_6730\",\"merchant_category\":\"electronics\",\"country\":\"IN\",\"city\":\"Bangalore\",\"timestamp\":\"2026-03-06 11:36:57.310831\",\"fraud_reason\":\"high_amount\"},\"maxValues\":{\"transaction_id\":\"TEST-FRAUD-001\",\"user_id\":\"USR_0058\",\"amount\":1500.0,\"currency\":\"USD\",\"merchant_id\":\"MER_9999\",\"merchant_category\":\"gas_station\",\"country\":\"US\",\"city\":\"New York\",\"timestamp\":\"2026-03-06 11:36:57.416285\",\"fraud_reason\":\"high_amount\"},\"nullCount\":{\"transaction_id\":0,\"user_id\":0,\"amount\":0,\"currency\":0,\"merchant_id\":0,\"merchant_category\":0,\"country\":0,\"city\":0,\"timestamp\":0,\"is_fraud\":0,\"fraud_type\":2,\"fraud_flag\":0,\"fraud_reason\":1}}"}}
